ShiyanlouSqlJiaochengHeji20160904Fix1/README.md
ShiyanlouSqlJiaochengHeji20160904Fix1/__init__.py
ShiyanlouSqlJiaochengHeji20160904Fix1/__main__.py
ShiyanlouSqlJiaochengHeji20160904Fix1/file.epub
ShiyanlouSqlJiaochengHeji20160904Fix1/index.html
ShiyanlouSqlJiaochengHeji20160904Fix1/css/__init__.py
ShiyanlouSqlJiaochengHeji20160904Fix1/css/annotations.css
ShiyanlouSqlJiaochengHeji20160904Fix1/css/main.css
ShiyanlouSqlJiaochengHeji20160904Fix1/css/normalize.css
ShiyanlouSqlJiaochengHeji20160904Fix1/css/popup.css
ShiyanlouSqlJiaochengHeji20160904Fix1/font/__init__.py
ShiyanlouSqlJiaochengHeji20160904Fix1/font/fontello.eot
ShiyanlouSqlJiaochengHeji20160904Fix1/font/fontello.svg
ShiyanlouSqlJiaochengHeji20160904Fix1/font/fontello.ttf
ShiyanlouSqlJiaochengHeji20160904Fix1/font/fontello.woff
ShiyanlouSqlJiaochengHeji20160904Fix1/img/__init__.py
ShiyanlouSqlJiaochengHeji20160904Fix1/img/annotator-glyph-sprite.png
ShiyanlouSqlJiaochengHeji20160904Fix1/img/annotator-icon-sprite.png
ShiyanlouSqlJiaochengHeji20160904Fix1/img/apple-touch-icon.png
ShiyanlouSqlJiaochengHeji20160904Fix1/img/cancelfullscreen.png
ShiyanlouSqlJiaochengHeji20160904Fix1/img/close.png
ShiyanlouSqlJiaochengHeji20160904Fix1/img/fullscreen.png
ShiyanlouSqlJiaochengHeji20160904Fix1/img/loader.gif
ShiyanlouSqlJiaochengHeji20160904Fix1/img/menu-icon.png
ShiyanlouSqlJiaochengHeji20160904Fix1/img/save.png
ShiyanlouSqlJiaochengHeji20160904Fix1/img/saved.png
ShiyanlouSqlJiaochengHeji20160904Fix1/img/settings-s.png
ShiyanlouSqlJiaochengHeji20160904Fix1/img/settings.png
ShiyanlouSqlJiaochengHeji20160904Fix1/img/star.png
ShiyanlouSqlJiaochengHeji20160904Fix1/js/__init__.py
ShiyanlouSqlJiaochengHeji20160904Fix1/js/epub.js
ShiyanlouSqlJiaochengHeji20160904Fix1/js/epub.min.js
ShiyanlouSqlJiaochengHeji20160904Fix1/js/epub.min.map
ShiyanlouSqlJiaochengHeji20160904Fix1/js/hooks.min.js
ShiyanlouSqlJiaochengHeji20160904Fix1/js/hooks.min.map
ShiyanlouSqlJiaochengHeji20160904Fix1/js/reader.js
shiyanlou_sql_jiaocheng_heji_20160904_fix1-2024.3.2.0.dist-info/METADATA
shiyanlou_sql_jiaocheng_heji_20160904_fix1-2024.3.2.0.dist-info/WHEEL
shiyanlou_sql_jiaocheng_heji_20160904_fix1-2024.3.2.0.dist-info/entry_points.txt
shiyanlou_sql_jiaocheng_heji_20160904_fix1-2024.3.2.0.dist-info/top_level.txt
shiyanlou_sql_jiaocheng_heji_20160904_fix1-2024.3.2.0.dist-info/RECORD
